march_history/__init__.py
march_history/_base_client.py
march_history/_version.py
march_history/client.py
march_history/config.py
march_history/exceptions.py
march_history/pagination.py
march_history/_async/__init__.py
march_history/_async/_base_client.py
march_history/_async/client.py
march_history/_async/resources/__init__.py
march_history/_async/resources/_base.py
march_history/_async/resources/conversations.py
march_history/_async/resources/messages.py
march_history/_async/resources/tenants.py
march_history/models/__init__.py
march_history/models/common.py
march_history/models/conversation.py
march_history/models/message.py
march_history/models/requests.py
march_history/models/tenant.py
march_history/resources/__init__.py
march_history/resources/_base.py
march_history/resources/conversations.py
march_history/resources/messages.py
march_history/resources/tenants.py
march_history-0.2.2.dist-info/METADATA
march_history-0.2.2.dist-info/WHEEL
march_history-0.2.2.dist-info/licenses/LICENSE
march_history-0.2.2.dist-info/RECORD
