Metadata-Version: 2.4
Name: march-history
Version: 0.2.2
Summary: Python SDK for March AI Conversation History API
Project-URL: Homepage, https://github.com/march-us/march-lib/march-conversation-history-python-sdk
Project-URL: Documentation, https://github.com/march-us/march-lib/march-conversation-history-python-sdk#readme
Project-URL: Repository, https://github.com/march-us/march-lib
Project-URL: Issues, https://github.com/march-us/march-lib/issues
Author: March Team
License: MIT
License-File: LICENSE
Keywords: ai,api,conversation,history,sdk
Classifier: Development Status :: 4 - Beta
Classifier: Intended Audience :: Developers
Classifier: License :: OSI Approved :: MIT License
Classifier: Programming Language :: Python :: 3
Classifier: Programming Language :: Python :: 3.11
Classifier: Programming Language :: Python :: 3.12
Classifier: Programming Language :: Python :: 3.13
Classifier: Typing :: Typed
Requires-Python: >=3.11
Requires-Dist: httpx>=0.25.0
Requires-Dist: pydantic>=2.0.0
Provides-Extra: dev
Requires-Dist: mypy>=1.5.0; extra == 'dev'
Requires-Dist: pytest-asyncio>=0.21.0; extra == 'dev'
Requires-Dist: pytest>=7.4.0; extra == 'dev'
Requires-Dist: respx>=0.20.0; extra == 'dev'
Requires-Dist: ruff>=0.1.0; extra == 'dev'
